tdmlplus/__init__.py
tdmlplus/patch/__init__.py
tdmlplus/patch/_dataframe_lineage_utils.py
tdmlplus/patch/_plotting_utils.py
tdmlplus/patch/dataframe.py
tdmlplus/patch/dataframe_column.py
tdmlplus/patch/dba.py
tdmlplus/patch/random.py
tdmlplus/patch/utils.py
tdmlplus/patch/widgets.py
teradataml_plus-0.3.1.dist-info/LICENSE
teradataml_plus-0.3.1.dist-info/METADATA
teradataml_plus-0.3.1.dist-info/WHEEL
teradataml_plus-0.3.1.dist-info/top_level.txt
teradataml_plus-0.3.1.dist-info/RECORD
