Metadata-Version: 2.1
Name: teradataml-plus
Version: 0.3.1
Summary: Python Package that extends the functionality of the popular teradataml package through monkey-patching.
Author: Martin Hillebrand
Author-email: martin.hillebrand@teradata.com
Keywords: teradataml-plus,teradata,database,teradataml
Classifier: Development Status :: 3 - Alpha
Classifier: Intended Audience :: Developers
Classifier: License :: OSI Approved :: GNU General Public License v3 (GPLv3)
Classifier: Natural Language :: English
Classifier: Programming Language :: Python :: 3
Classifier: Programming Language :: Python :: 3.9
Classifier: Programming Language :: Python :: 3.10
Classifier: Programming Language :: Python :: 3.11
Classifier: Programming Language :: Python :: 3.12
Classifier: Topic :: Database
Requires-Python: >=3.9
License-File: LICENSE
Requires-Dist: teradataml >=20.0.00.00
Requires-Dist: scikit-learn >=1.2.0
Requires-Dist: numpy >=1.24.2
Requires-Dist: sqlparse
Provides-Extra: plot
Requires-Dist: plotly >=5.0 ; extra == 'plot'
Requires-Dist: seaborn >=0.11 ; extra == 'plot'
Requires-Dist: networkx ; extra == 'plot'
Requires-Dist: sqlparse ; extra == 'plot'
